{
  "ID": "94325940",
  "Name": "ශ්‍රී ලංකාවේ ඓතිහාසික ස්ථාන -තුන්වන කාණ්ඩය ",
  "Description": "",
  "Tag": [
    "O/L",
    "",
    "A/L"
  ],
  "MapID": "sl-rivers",
  "Markers": {
    "be732d84": {
      "ID": "be732d84",
      "Name": "හැමන්හෛල්  ",
      "X": "144",
      "Y": "110",
      "R": "30"
    },
    "77c4582c": {
      "ID": "77c4582c",
      "Name": "ෆෙඩ්‍රික් කොටුව ",
      "X": "666",
      "Y": "532",
      "R": "30"
    },
    "3d8c9ee5": {
      "ID": "3d8c9ee5",
      "Name": "වෙල්ලස්ස ",
      "X": "706",
      "Y": "1128",
      "R": "30"
    },
    "190b5c01": {
      "ID": "190b5c01",
      "Name": "කුරුන්දි ",
      "X": "461",
      "Y": "257",
      "R": "30"
    },
    "2283d72e": {
      "ID": "2283d72e",
      "Name": "පොම්පරිප්පු ",
      "X": "166",
      "Y": "612",
      "R": "30"
    },
    "e6d262e3": {
      "ID": "e6d262e3",
      "Name": "මුන්නේශ්වරම ",
      "X": "159",
      "Y": "899",
      "R": "30"
    },
    "626b535e": {
      "ID": "626b535e",
      "Name": "අලකොළවැව",
      "X": "514",
      "Y": "782",
      "R": "30"
    },
    "3e57fc84": {
      "ID": "3e57fc84",
      "Name": "මුල්ලේරියාව ",
      "X": "185",
      "Y": "1152",
      "R": "30"
    },
    "70e25932": {
      "ID": "70e25932",
      "Name": "හෝර්ටන් තැන්න ",
      "X": "576",
      "Y": "1199",
      "R": "30"
    },
    "473f36d9": {
      "ID": "473f36d9",
      "Name": "දන්තුරේ ",
      "X": "430",
      "Y": "1013",
      "R": "30"
    },
    "74a40e10": {
      "ID": "74a40e10",
      "Name": "වාලුකාගාම",
      "X": "385",
      "Y": "1504",
      "R": "30"
    },
    "e7df0d08": {
      "ID": "e7df0d08",
      "Name": "මහානාගහුල",
      "X": "575",
      "Y": "1431",
      "R": "30"
    }
  },
  "Rivers": {}
}